exeu/__init__.py
exeu/core.py
exeustr/__init__.py
exeustr/core.py
exeustr-0.0.1.dist-info/LICENSE
exeustr-0.0.1.dist-info/METADATA
exeustr-0.0.1.dist-info/WHEEL
exeustr-0.0.1.dist-info/top_level.txt
exeustr-0.0.1.dist-info/RECORD
