Metadata-Version: 2.1
Name: exeustr
Version: 0.0.1
Summary: execute python code using string
Home-page: https://github.com/dulingkang/exeu
Author: dulingkang
Author-email: dulingkang@163.com
License: Apache-2.0 license
Project-URL: Bug Tracker, https://github.com/dulingkang/exeu/issues
Project-URL: Documentation, https://github.com/dulingkang/exeu
Project-URL: Source Code, https://github.com/dulingkang/exeu
Keywords: exeucate eval,pipy test,python instruction,
Classifier: Natural Language :: English
Classifier: Operating System :: OS Independent
Classifier: Programming Language :: Python
Classifier: Programming Language :: Python :: 3
Classifier: Programming Language :: Python :: 3.7
Classifier: Programming Language :: Python :: 3.8
Classifier: Programming Language :: Python :: 3.9
Classifier: Programming Language :: Python :: 3.10
Classifier: Intended Audience :: Science/Research
Classifier: License :: OSI Approved :: Apache Software License
Classifier: Topic :: Scientific/Engineering :: Bio-Informatics
Classifier: Topic :: Scientific/Engineering :: Mathematics
Classifier: Topic :: Scientific/Engineering :: Artificial Intelligence
Classifier: Topic :: Software Development :: Libraries
Requires-Python: >=3.7
License-File: LICENSE
